toolbox_config-0.0.11-py3.6-nspkg.pth
toolbox/config/__init__.py
toolbox/config/cli.py
toolbox_config-0.0.11.dist-info/DESCRIPTION.rst
toolbox_config-0.0.11.dist-info/METADATA
toolbox_config-0.0.11.dist-info/RECORD
toolbox_config-0.0.11.dist-info/WHEEL
toolbox_config-0.0.11.dist-info/entry_points.txt
toolbox_config-0.0.11.dist-info/metadata.json
toolbox_config-0.0.11.dist-info/namespace_packages.txt
toolbox_config-0.0.11.dist-info/top_level.txt
