Metadata-Version: 2.0
Name: toolbox-config
Version: 0.0.11
Summary: Tooling to manage project configs for production, staging, local, etc
Home-page: http://github.com/nziehn/toolbox-config
Author: Nils Ziehn
Author-email: nziehn@gmail.com
License: MIT
Platform: UNKNOWN
Requires-Dist: PyYAML (>=3.0)
Requires-Dist: boto3 (>=1.8.0)
Requires-Dist: cachetools (>=3.0.0)
Requires-Dist: jsonpath-ng
